[
  {
    "id": "18a4208e-4762-4fbb-953f-27ce45aafdaf",
    "data": [
      {
        "text": "go ahead",
        "alias": "issue-parameters",
        "meta": "@issue-parameters",
        "userDefined": true
      }
    ],
    "isTemplate": false,
    "count": 0
  },
  {
    "id": "78ca0f6d-01ca-4781-84f1-87bdfb07b941",
    "data": [
      {
        "text": "Of course",
        "alias": "issue-parameters",
        "meta": "@issue-parameters",
        "userDefined": true
      }
    ],
    "isTemplate": false,
    "count": 0
  },
  {
    "id": "66da8428-6970-4bb4-aa1f-98871be1b226",
    "data": [
      {
        "text": "Oh, ",
        "userDefined": false
      },
      {
        "text": "no",
        "alias": "issue-parameters",
        "meta": "@issue-parameters",
        "userDefined": true
      }
    ],
    "isTemplate": false,
    "count": 0
  },
  {
    "id": "490268d8-faf6-489a-ab9b-b368e50df64a",
    "data": [
      {
        "text": "sure",
        "alias": "issue-parameters",
        "meta": "@issue-parameters",
        "userDefined": true
      }
    ],
    "isTemplate": false,
    "count": 0
  },
  {
    "id": "2874b6ed-c07d-4dde-bd85-5c04f0ababf2",
    "data": [
      {
        "text": "No",
        "userDefined": false
      }
    ],
    "isTemplate": false,
    "count": 0
  },
  {
    "id": "d67b67db-e5b9-427e-b24a-e254a02d4ef3",
    "data": [
      {
        "text": "Yes",
        "alias": "issue-parameters",
        "meta": "@issue-parameters",
        "userDefined": true
      }
    ],
    "isTemplate": false,
    "count": 0
  },
  {
    "id": "3b6e7b19-55bf-47ee-8704-fa8ab20e111c",
    "data": [
      {
        "text": "all",
        "userDefined": false
      }
    ],
    "isTemplate": false,
    "count": 0
  },
  {
    "id": "8eb908a4-5a15-4770-a291-8c2fd53ff0b9",
    "data": [
      {
        "text": "all issues",
        "userDefined": false
      }
    ],
    "isTemplate": false,
    "count": 0
  },
  {
    "id": "bc321e8c-1011-4f91-9b95-d65c850a0f3b",
    "data": [
      {
        "text": "show",
        "alias": "issue-list",
        "meta": "@issue-list",
        "userDefined": false
      },
      {
        "text": " ",
        "userDefined": false
      },
      {
        "text": "9",
        "alias": "issue-id",
        "meta": "@sys.number-integer",
        "userDefined": false
      }
    ],
    "isTemplate": false,
    "count": 0
  },
  {
    "id": "9c122d6f-73bf-42a5-8d95-3255941a5225",
    "data": [
      {
        "text": "get",
        "alias": "issue-list",
        "meta": "@issue-list",
        "userDefined": false
      },
      {
        "text": " ",
        "userDefined": false
      },
      {
        "text": "1",
        "alias": "issue-id",
        "meta": "@sys.number-integer",
        "userDefined": false
      }
    ],
    "isTemplate": false,
    "count": 0
  },
  {
    "id": "959492d1-c33d-4951-a7ef-2da6168d4234",
    "data": [
      {
        "text": "list",
        "alias": "issue-list",
        "meta": "@issue-list",
        "userDefined": false
      },
      {
        "text": " ",
        "userDefined": false
      },
      {
        "text": "8",
        "alias": "issue-id",
        "meta": "@sys.number-integer",
        "userDefined": false
      }
    ],
    "isTemplate": false,
    "count": 0
  },
  {
    "id": "f1f301c5-5bb5-4a2d-b355-440618a8d10f",
    "data": [
      {
        "text": "10",
        "alias": "issue-id",
        "meta": "@sys.number-integer",
        "userDefined": false
      }
    ],
    "isTemplate": false,
    "count": 0
  },
  {
    "id": "2a0904bb-6486-410f-831a-1387cf9c1a7b",
    "data": [
      {
        "text": "6",
        "alias": "issue-id",
        "meta": "@sys.number-integer",
        "userDefined": false
      }
    ],
    "isTemplate": false,
    "count": 0
  },
  {
    "id": "bda1c6d2-53d1-4972-b5a0-1dff0fc85cb7",
    "data": [
      {
        "text": "list",
        "alias": "issue-list",
        "meta": "@issue-list",
        "userDefined": true
      },
      {
        "text": " issue ",
        "userDefined": false
      },
      {
        "text": "6",
        "alias": "issue-id",
        "meta": "@sys.number-integer",
        "userDefined": true
      }
    ],
    "isTemplate": false,
    "count": 0
  },
  {
    "id": "a74bcb4c-fef1-438c-9b1b-6945adfa0a34",
    "data": [
      {
        "text": "get",
        "alias": "issue-list",
        "meta": "@issue-list",
        "userDefined": true
      },
      {
        "text": " issue",
        "userDefined": false
      },
      {
        "text": " 5",
        "alias": "issue-id",
        "meta": "@sys.number-integer",
        "userDefined": true
      }
    ],
    "isTemplate": false,
    "count": 0
  },
  {
    "id": "18aa9d74-956f-4775-afd8-409253a766ea",
    "data": [
      {
        "text": "show",
        "alias": "issue-list",
        "meta": "@issue-list",
        "userDefined": true
      },
      {
        "text": " me issue ",
        "userDefined": false
      },
      {
        "text": "4",
        "alias": "issue-id",
        "meta": "@sys.number-integer",
        "userDefined": true
      }
    ],
    "isTemplate": false,
    "count": 0
  },
  {
    "id": "1802ac80-189d-4c8e-89a6-e35817db1f3b",
    "data": [
      {
        "text": "list",
        "alias": "issue-list",
        "meta": "@issue-list",
        "userDefined": true
      },
      {
        "text": " issues for me",
        "userDefined": false
      }
    ],
    "isTemplate": false,
    "count": 0,
    "updated": 1513087425
  }
]